virtualizor_forwarding/__init__.py
virtualizor_forwarding/__main__.py
virtualizor_forwarding/api.py
virtualizor_forwarding/cli.py
virtualizor_forwarding/config.py
virtualizor_forwarding/models.py
virtualizor_forwarding/tui.py
virtualizor_forwarding/updater.py
virtualizor_forwarding/utils.py
virtualizor_forwarding/services/__init__.py
virtualizor_forwarding/services/batch_processor.py
virtualizor_forwarding/services/forwarding_manager.py
virtualizor_forwarding/services/vm_manager.py
virtualizor_forwarding-1.0.7.dist-info/METADATA
virtualizor_forwarding-1.0.7.dist-info/WHEEL
virtualizor_forwarding-1.0.7.dist-info/entry_points.txt
virtualizor_forwarding-1.0.7.dist-info/top_level.txt
virtualizor_forwarding-1.0.7.dist-info/RECORD
