Metadata-Version: 2.4
Name: virtualizor-forwarding
Version: 1.0.7
Summary: CLI tool for managing domain/port forwarding in Virtualizor VPS environments with multi-host support
Author-email: Rizky Adhy Pratama <rizkyadhypratama@gmail.com>
License: MIT
Project-URL: Homepage, https://rizzcode.id
Project-URL: Repository, https://github.com/iam-rizz/python-domain-forwarding-virtualizor.git
Project-URL: Issues, https://github.com/iam-rizz/python-domain-forwarding-virtualizor/issues
Keywords: virtualizor,vps,port-forwarding,domain-forwarding,cli
Classifier: Development Status :: 4 - Beta
Classifier: Environment :: Console
Classifier: Intended Audience :: System Administrators
Classifier: License :: OSI Approved :: MIT License
Classifier: Operating System :: OS Independent
Classifier: Programming Language :: Python :: 3
Classifier: Programming Language :: Python :: 3.8
Classifier: Programming Language :: Python :: 3.9
Classifier: Programming Language :: Python :: 3.10
Classifier: Programming Language :: Python :: 3.11
Classifier: Programming Language :: Python :: 3.12
Classifier: Programming Language :: Python :: 3.13
Classifier: Topic :: System :: Systems Administration
Requires-Python: >=3.8
Requires-Dist: requests>=2.28.0
Requires-Dist: rich>=13.0.0
Provides-Extra: dev
Requires-Dist: pytest>=7.0.0; extra == "dev"
Requires-Dist: hypothesis>=6.0.0; extra == "dev"
Requires-Dist: pytest-cov>=4.0.0; extra == "dev"
Requires-Dist: responses>=0.23.0; extra == "dev"
